jrcf-0.5.0.dist-info/METADATA
jrcf-0.5.0.dist-info/WHEEL
jrcf-0.5.0.dist-info/entry_points.txt
jrcf-0.5.0.dist-info/licenses/LICENSE
jrcf/__init__.py
jrcf/__version__.py
jrcf/lib/jackson-annotations-2.19.0.jar
jrcf/lib/jackson-core-2.19.0.jar
jrcf/lib/jackson-databind-2.19.0.jar
jrcf/lib/randomcutforest-core-4.3.0.jar
jrcf/lib/randomcutforest-parkservices-4.3.0.jar
jrcf/rcf.py
jrcf-0.5.0.dist-info/RECORD
