Metadata-Version: 2.1
Name: jrcf
Version: 0.5.0
Summary: AWS's Java Random Cut Forest
Keywords: rcf,random-cut-forest,anomaly-detection
Author-Email: Dowon <ks2515@naver.com>
License: Apache-2.0
Classifier: Intended Audience :: Developers
Classifier: Intended Audience :: Science/Research
Classifier: Programming Language :: Java
Classifier: Programming Language :: Python :: 3 :: Only
Project-URL: Repository, https://github.com/Bing-su/jrcf
Requires-Python: >=3.10
Requires-Dist: jpype1
Requires-Dist: numpy>=1.21
